.gitignore
AUTHORS
COPYING
INSTALL
MANIFEST.in
NEWS
PKG-INFO.in
README
setup.py
docs/Makefile
docs/conf.py
docs/documentation.rst
docs/gettingstarted.rst
docs/index.rst
docs/api/adapters.rst
docs/api/controller.rst
docs/api/index.rst
docs/api/metaclasses.rst
docs/api/model.rst
docs/api/observable.rst
docs/api/observer.rst
docs/api/support.rst
docs/api/view.rst
docs/five_min/index.rst
docs/five_min/images/example1.png
docs/five_min/images/example2.png
docs/five_min/images/example_glade.png
docs/manual/adapt.rst
docs/manual/arch.rst
docs/manual/exam.rst
docs/manual/impl.rst
docs/manual/index.rst
docs/manual/install.rst
docs/manual/intro.rst
docs/manual/motiv.rst
docs/manual/mvc.rst
docs/manual/mvco.rst
docs/manual/obs.rst
docs/manual/observers.rst
docs/manual/op.rst
docs/manual/op_concrete.rst
docs/manual/op_constr.rst
docs/manual/op_logical.rst
docs/manual/op_special.rst
docs/manual/op_types.rst
docs/manual/progen.rst
docs/manual/images/adap.dia
docs/manual/images/adap.png
docs/manual/images/adap1.png
docs/manual/images/adap2.png
docs/manual/images/adap3.png
docs/manual/images/adapuml.dia
docs/manual/images/adapuml.png
docs/manual/images/arch.dia
docs/manual/images/arch.png
docs/manual/images/example.png
docs/manual/images/example_glade.png
docs/manual/images/main_classes.dia
docs/manual/images/main_classes.png
docs/manual/images/mvc.dia
docs/manual/images/mvc.png
docs/manual/images/obs.dia
docs/manual/images/obs.png
docs/manual/images/op_deps.dia
docs/manual/images/op_deps.png
docs/manual/images/treeview.png
docs/manual/images/widget.png
docs/quickstart/index.rst
docs/quickstart/images/diagram.dia
docs/quickstart/images/diagram.png
docs/quickstart/images/example.png
docs/quickstart/images/example2.png
docs/quickstart/images/example_glade.png
docs/quickstart/images/mvc.png
docs/quickstart/images/mvc_glade.png
docs/tutorial/common.rst
docs/tutorial/end.rst
docs/tutorial/index.rst
docs/tutorial/intro.rst
docs/tutorial/progen.rst
docs/tutorial/step1.rst
python_gtkmvc.egg-info/PKG-INFO
python_gtkmvc_dlr.egg-info/PKG-INFO
python_gtkmvc_dlr.egg-info/SOURCES.txt
python_gtkmvc_dlr.egg-info/dependency_links.txt
python_gtkmvc_dlr.egg-info/top_level.txt
