Metadata-Version: 1.1
Name: python-gtkmvc-dlr
Version: 1.99.2
Summary: Model-View-Controller and Observer patterns for developing pygtk-based applications -- mainly written by Roberto Cavadaand for minor changes forked by the Institute of Robotics and Mechatronics of the German Aerospace Center (DLR-RM). In order to release a full installation chain for other tools DLR-RM put it on pypi even so the previous versions were only hosted on sourceforge.net.
Home-page: https://github.com/DLR-RM/gtkmvc3/tree/gtkmvc_dlr
Author: Rico Belder
Author-email: rico.belder@dlr.de
License: LGPL
Download-URL: https://github.com/DLR-RM/gtkmvc3/releases/download/gtkmvc_dlr_1.99.2/python-gtkmvc-dlr-1.99.2.tar.gz
Platform: UNKNOWN
Classifier: Development Status :: 4 - Beta
Classifier: Environment :: Console
Classifier: Environment :: X11 Applications :: GTK Web Environment
Classifier: Intended Audience :: Developers
Classifier: License :: OSI Approved :: GNU Library or Lesser General Public License (LGPL)
Classifier: Operating System :: MacOS :: MacOS X
Classifier: Operating System :: Microsoft :: Windows
Classifier: Operating System :: POSIX
Classifier: Programming Language :: Python
Classifier: Topic :: Software Development :: User Interfaces
Classifier: Topic :: Software Development :: Libraries :: Application Frameworks
